arx_x5_sdk/__init__.py
arx_x5_sdk/arx_x5_sdk.cpython-310-x86_64-linux-gnu.so
arx_x5_sdk/libarx_x5_src.so
arx_x5_sdk/urdf/x5.urdf
arx_x5_sdk/urdf/x5_2025.urdf
arx_x5_sdk/urdf/x5_master.urdf
arx_x5_sdk-0.1.2.dist-info/licenses/LICENSE
arx_x5_sdk-0.1.2.dist-info/METADATA
arx_x5_sdk-0.1.2.dist-info/WHEEL
arx_x5_sdk-0.1.2.dist-info/top_level.txt
arx_x5_sdk-0.1.2.dist-info/RECORD
