Metadata-Version: 2.4
Name: arx-x5-sdk
Version: 0.1.2
Summary: ARX X5 Robot Arm Python SDK
Author: Remi Cadene, UMA
Author-email: Remi Cadene <remi@uma.bot>, UMA <contact@uma.bot>
License-Expression: BSD-3-Clause
Project-URL: Homepage, https://github.com/uma-robots/arx-x5-sdk
Project-URL: Repository, https://github.com/uma-robots/arx-x5-sdk
Project-URL: Issues, https://github.com/uma-robots/arx-x5-sdk/issues
Keywords: robotics,arx,robot-arm,sdk
Classifier: Development Status :: 3 - Alpha
Classifier: Intended Audience :: Developers
Classifier: Programming Language :: Python :: 3
Classifier: Programming Language :: Python :: 3.10
Classifier: Programming Language :: Python :: 3.11
Classifier: Programming Language :: Python :: 3.12
Classifier: Programming Language :: C++
Classifier: Topic :: Scientific/Engineering
Requires-Python: >=3.10
License-File: LICENSE
Requires-Dist: pybind11>=2.10.0
Dynamic: author
Dynamic: license-file
Dynamic: requires-python
